asyncio_anywhere/__init__.py
asyncio_anywhere/core.py
asyncio_anywhere/py.typed
asyncio_anywhere-0.2.0.dist-info/LICENSE
asyncio_anywhere-0.2.0.dist-info/METADATA
asyncio_anywhere-0.2.0.dist-info/WHEEL
asyncio_anywhere-0.2.0.dist-info/RECORD
