Metadata-Version: 2.1
Name: asyncio-anywhere
Version: 0.2.0
Summary: Python package that makes it easy to run fast asyncio code
Home-page: https://github.com/novex-ai/asyncio-anywhere
License: MIT
Keywords: python,asyncio,jupyter,trio,curio
Author: Brad Ito
Author-email: phlogisticfugu@gmail.com
Requires-Python: >=3.8,<4.0
Classifier: License :: OSI Approved :: MIT License
Classifier: Programming Language :: Python :: 3
Classifier: Programming Language :: Python :: 3.8
Classifier: Programming Language :: Python :: 3.9
Classifier: Programming Language :: Python :: 3.10
Classifier: Programming Language :: Python :: 3.11
Requires-Dist: uvloop (>=0.19.0,<0.20.0) ; sys_platform == "linux" or sys_platform == "darwin"
Project-URL: Changelog, https://github.com/novex-ai/asyncio-anywhere/releases
Project-URL: Issues, https://github.com/novex-ai/asyncio-anywhere/issues
Project-URL: Repository, https://github.com/novex-ai/asyncio-anywhere
